{
  "description": "image conversion",
  "enable": true,
  "notShowInMenu": true,
  "imageTypeConversion": {
    "imageTypes": [
      {
        "name": "numpy.ndarray",
        "functionName": "numpyndarray2numpyndarray",
        "function": "def numpyndarray2numpyndarray(): return 'numpyndarray2numpyndarray'"
      },
      {
        "name": "torch.tensor",
        "functionName": "torchtensor2torchtensor",
        "function": "def torchtensor2torchtensor(): return 'torchtensor2torchtensor'"
      }
    ],
    "ImageTypeConversions": [
      {
        "from": "numpy.ndarray",
        "to": "torch.tensor",
        "functionName": "numpyndarrayToTorchtensor",
        "function": "def numpyndarrayToTorchtensor(): return 'numpyndarrayToTorchtensor'"
      },
      {
        "from": "torch.tensor",
        "to": "numpy.ndarray",
        "functionName": "torchtensorToNumpyndarray",
        "function": "def torchtensorToNumpyndarray(): return 'torchtensorToNumpyndarray'"
      }
    ]
  }
}
